closedexpressions/__init__.py
closedexpressions/distributions.py
closedexpressions/excess_time_statistics.py
closedexpressions/second_order_statistics.py
closedexpressions-0.1.2.dist-info/LICENSE
closedexpressions-0.1.2.dist-info/WHEEL
closedexpressions-0.1.2.dist-info/METADATA
closedexpressions-0.1.2.dist-info/RECORD
